freezefrog/__init__.py
freezefrog-0.3.dist-info/DESCRIPTION.rst
freezefrog-0.3.dist-info/METADATA
freezefrog-0.3.dist-info/metadata.json
freezefrog-0.3.dist-info/RECORD
freezefrog-0.3.dist-info/top_level.txt
freezefrog-0.3.dist-info/WHEEL
