Metadata-Version: 2.0
Name: freezefrog
Version: 0.3
Summary: Efficient datetime mocking in tests
Home-page: http://github.com/closeio/freezefrog
Author: Thomas Steinacher
Author-email: engineering@close.io
License: MIT
Platform: any
Classifier: Intended Audience :: Developers
Classifier: License :: OSI Approved :: MIT License
Classifier: Operating System :: OS Independent
Classifier: Topic :: Software Development :: Libraries :: Python Modules
Classifier: Programming Language :: Python
Classifier: Programming Language :: Python :: 2
Classifier: Programming Language :: Python :: 2.7
Classifier: Programming Language :: Python :: 3
Classifier: Programming Language :: Python :: 3.4
Classifier: Programming Language :: Python :: 3.5
Requires-Dist: mock
